chartly/__init__.py
chartly/base.py
chartly/chartly.py
chartly/charts.py
chartly/utilities.py
chartly-0.0.4.dist-info/LICENSE
chartly-0.0.4.dist-info/METADATA
chartly-0.0.4.dist-info/WHEEL
chartly-0.0.4.dist-info/top_level.txt
chartly-0.0.4.dist-info/RECORD
