Metadata-Version: 2.1
Name: chartly
Version: 0.0.4
Summary: A Python package for chartly multiple plots.
Home-page: https://github.com/ec-intl/chartly
Author: Elizabeth Consulting International Inc.
Author-email: info@ec-intl.com
License: Apache License 2.0
Project-URL: Homepage, https://github.com/ec-intl/chartly
Project-URL: Issues, https://github.com/ec-intl/chartly/issues
Classifier: Programming Language :: Python :: 3
Classifier: License :: OSI Approved :: Apache Software License
Classifier: Operating System :: OS Independent
Requires-Python: >=3.6
License-File: LICENSE
